thlink_backend_app_lib/__init__.py
thlink_backend_app_lib/base_model.py
thlink_backend_app_lib/communication.py
thlink_backend_app_lib/lazy.py
thlink_backend_app_lib/middleware.py
thlink_backend_app_lib-0.6.3.dist-info/LICENSE
thlink_backend_app_lib-0.6.3.dist-info/WHEEL
thlink_backend_app_lib-0.6.3.dist-info/METADATA
thlink_backend_app_lib-0.6.3.dist-info/RECORD
