Metadata-Version: 2.1
Name: thlink-backend-app-lib
Version: 0.6.3
Summary: 
Author: thlink
Requires-Python: >=3.7,<4.0
Classifier: Programming Language :: Python :: 3
Classifier: Programming Language :: Python :: 3.7
Classifier: Programming Language :: Python :: 3.8
Classifier: Programming Language :: Python :: 3.9
Requires-Dist: aws-lambda-powertools (>=1.16,<2.0)
Requires-Dist: pydantic (>=1.8.2,<2.0.0)
